pytask_environment/__init__.py
pytask_environment/_version.py
pytask_environment/config.py
pytask_environment/database.py
pytask_environment/logging.py
pytask_environment/plugin.py
pytask_environment-0.3.0.dist-info/LICENSE
pytask_environment-0.3.0.dist-info/METADATA
pytask_environment-0.3.0.dist-info/WHEEL
pytask_environment-0.3.0.dist-info/entry_points.txt
pytask_environment-0.3.0.dist-info/top_level.txt
pytask_environment-0.3.0.dist-info/RECORD
