Metadata-Version: 2.1
Name: pytask-environment
Version: 0.3.0
Summary: Detect changes in your pytask environment and abort a project build.
Home-page: https://github.com/pytask-dev/pytask-environment
Author: Tobias Raabe
Author-email: raabe@posteo.de
License: MIT
Project-URL: Changelog, https://github.com/pytask-dev/pytask-environment/blob/main/CHANGES.md
Project-URL: Documentation, https://github.com/pytask-dev/pytask-environment
Project-URL: Github, https://github.com/pytask-dev/pytask-environment
Project-URL: Tracker, https://github.com/pytask-dev/pytask-environment/issues
Platform: any
Classifier: Development Status :: 4 - Beta
Classifier: License :: OSI Approved :: MIT License
Classifier: Operating System :: OS Independent
Classifier: Programming Language :: Python :: 3
Classifier: Programming Language :: Python :: 3 :: Only
Requires-Python: >=3.7
License-File: LICENSE
Requires-Dist: click
Requires-Dist: pony
Requires-Dist: pytask (>=0.2)
